terracomp_api/__init__.py
terracomp_api/_client.py
terracomp_api/grpc/.gitignore
terracomp_api/py.typed
terracomp_api-0.0.8.dist-info/LICENSE
terracomp_api-0.0.8.dist-info/METADATA
terracomp_api-0.0.8.dist-info/WHEEL
terracomp_api-0.0.8.dist-info/RECORD
